CHANGES.txt
DEPENDENCES.txt
README.txt
setup.py
src/ng/__init__.py
src/ng.base.form.egg-info/PKG-INFO
src/ng.base.form.egg-info/SOURCES.txt
src/ng.base.form.egg-info/dependency_links.txt
src/ng.base.form.egg-info/namespace_packages.txt
src/ng.base.form.egg-info/not-zip-safe
src/ng.base.form.egg-info/requires.txt
src/ng.base.form.egg-info/top_level.txt
src/ng/base/__init__.py
src/ng/base/form/__init__.py
src/ng/base/form/configure.zcml
src/ng/base/form/formcontainer.py
src/ng/base/form/formint.py
src/ng/base/form/formitembase.py
src/ng/base/form/formregexp.py
src/ng/base/form/formtext.py
src/ng/base/form/formtextline.py
src/ng/base/form/interfaces.py
src/ng/base/form/ng.base.form.txt
src/ng/base/form/browser/__init__.py
src/ng/base/form/browser/configure.zcml
src/ng/base/form/browser/dialog.pt
src/ng/base/form/browser/dialog.py
src/ng/base/form/browser/dialognamespace.py
src/ng/base/form/browser/formedit.py
src/ng/base/form/browser/formsave.py
src/ng/base/form/etc/ng.base.form-configure.zcml